bindings/README.md
bindings/__init__.py
bindings/python/__init__.py
bindings/python/zlsp/__init__.py
core/README.md
core/__init__.py
core/cli.py
core/exceptions.py
core/lsp_types.py
core/version.py
core/parser/__init__.py
core/parser/constants.py
core/parser/parser.py
core/parser/parser_modules/__init__.py
core/parser/parser_modules/block_tracker.py
core/parser/parser_modules/comment_processors.py
core/parser/parser_modules/error_formatter.py
core/parser/parser_modules/escape_processors.py
core/parser/parser_modules/file_type_detector.py
core/parser/parser_modules/key_detector.py
core/parser/parser_modules/line_parsers.py
core/parser/parser_modules/multiline_collectors.py
core/parser/parser_modules/serializer.py
core/parser/parser_modules/token_emitter.py
core/parser/parser_modules/token_emitters.py
core/parser/parser_modules/type_hints.py
core/parser/parser_modules/validators.py
core/parser/parser_modules/value_processors.py
core/parser/parser_modules/value_validators.py
core/providers/__init__.py
core/providers/completion_provider.py
core/providers/diagnostics_engine.py
core/providers/hover_provider.py
core/providers/provider_modules/__init__.py
core/providers/provider_modules/completion_registry.py
core/providers/provider_modules/diagnostic_formatter.py
core/providers/provider_modules/documentation_registry.py
core/providers/provider_modules/hover_renderer.py
core/server/__init__.py
core/server/lsp_server.py
core/server/semantic_tokenizer.py
editors/README.md
editors/__init__.py
editors/vim/QUICKSTART.md
editors/vim/README.md
editors/vim/VIM_INTEGRATION.md
editors/vim/__init__.py
editors/vim/__main__.py
editors/vim/install.py
editors/vim/install.sh
editors/vim/setup_vim_lsp.sh
editors/vim/uninstall.py
editors/vim/config/lsp_config.vim
editors/vim/config/vimrc_snippet.vim
editors/vim/config/zolo_highlights.vim
editors/vim/config/after/ftplugin/zolo.vim
editors/vim/config/after/syntax/zolo.vim
editors/vim/config/colors/zolo_lsp.vim
zlsp-1.0.0.dist-info/licenses/LICENSE
zlsp-1.0.0.dist-info/METADATA
zlsp-1.0.0.dist-info/WHEEL
zlsp-1.0.0.dist-info/entry_points.txt
zlsp-1.0.0.dist-info/top_level.txt
zlsp-1.0.0.dist-info/RECORD
