Metadata-Version: 2.4
Name: zlsp
Version: 1.0.0
Summary: Modern Language Server Protocol (LSP) for .zolo files with semantic highlighting, validation, and Vim integration
Author-email: Gal Nachshon <hello@zolo.ai>
Maintainer-email: Gal Nachshon <hello@zolo.ai>
License: MIT with Ethical Use Clause
Project-URL: Homepage, https://github.com/ZoloAi/ZoloMedia
Project-URL: Documentation, https://github.com/ZoloAi/ZoloMedia/tree/main/zlsp
Project-URL: Repository, https://github.com/ZoloAi/ZoloMedia
Project-URL: Bug Tracker, https://github.com/ZoloAi/ZoloMedia/issues
Keywords: zlsp,zolo,lsp,language-server,language-server-protocol,parser,semantic-highlighting,vim,neovim,declarative,configuration,syntax-highlighting
Classifier: Development Status :: 4 - Beta
Classifier: Intended Audience :: Developers
Classifier: License :: OSI Approved :: MIT License
Classifier: Programming Language :: Python :: 3
Classifier: Programming Language :: Python :: 3.8
Classifier: Programming Language :: Python :: 3.9
Classifier: Programming Language :: Python :: 3.10
Classifier: Programming Language :: Python :: 3.11
Classifier: Programming Language :: Python :: 3.12
Classifier: Programming Language :: Python :: 3 :: Only
Classifier: Topic :: Software Development :: Libraries :: Python Modules
Classifier: Topic :: Software Development :: Code Generators
Classifier: Topic :: Software Development :: Compilers
Classifier: Topic :: Text Processing :: Markup
Classifier: Topic :: Text Editors :: Integrated Development Environments (IDE)
Classifier: Operating System :: OS Independent
Classifier: Operating System :: MacOS
Classifier: Operating System :: POSIX :: Linux
Classifier: Environment :: Console
Classifier: Typing :: Typed
Requires-Python: >=3.8
Requires-Dist: pygls>=1.3.0
Requires-Dist: lsprotocol>=2023.0.0
Provides-Extra: dev
Requires-Dist: pytest>=7.0; extra == "dev"
Requires-Dist: pytest-cov>=4.0; extra == "dev"
Requires-Dist: black>=23.0; extra == "dev"
Requires-Dist: mypy>=1.0; extra == "dev"
Requires-Dist: ruff>=0.1.0; extra == "dev"
Provides-Extra: themes
Requires-Dist: pyyaml>=6.0; extra == "themes"
Provides-Extra: all
Requires-Dist: zlsp[dev,themes]; extra == "all"
